eth_multicall/Constants.py
eth_multicall/Function.py
eth_multicall/MultiCall.py
eth_multicall/MultiChain.py
eth_multicall/__init__.py
eth_multicall/custome_types.py
eth_multicall-0.2.2.dist-info/WHEEL
eth_multicall-0.2.2.dist-info/METADATA
eth_multicall-0.2.2.dist-info/RECORD
